nti.fakestatsd-1.0.0-py3.7-nspkg.pth
nti/fakestatsd/__init__.py
nti/fakestatsd/client.py
nti/fakestatsd/matchers.py
nti/fakestatsd/metric.py
nti/fakestatsd/tests/__init__.py
nti/fakestatsd/tests/test_client.py
nti/fakestatsd/tests/test_matchers.py
nti/fakestatsd/tests/test_metric.py
nti.fakestatsd-1.0.0.dist-info/AUTHORS
nti.fakestatsd-1.0.0.dist-info/LICENSE
nti.fakestatsd-1.0.0.dist-info/METADATA
nti.fakestatsd-1.0.0.dist-info/WHEEL
nti.fakestatsd-1.0.0.dist-info/namespace_packages.txt
nti.fakestatsd-1.0.0.dist-info/top_level.txt
nti.fakestatsd-1.0.0.dist-info/zip-safe
nti.fakestatsd-1.0.0.dist-info/RECORD
