Metadata-Version: 2.1
Name: nti.fakestatsd
Version: 1.0.0
Summary: Testing StatsD client
Home-page: https://github.com/NextThought/nti.fakestatsd/
Author: Chris Utz
Author-email: open-source@nextthought.com
License: Apache
Project-URL: Bug Tracker, https://github.com/NextThought/nti.fakestatsd/issues
Project-URL: Source Code, https://github.com/NextThought/nti.fakestatsd/
Project-URL: Documentation, https://ntifakestatsd.readthedocs.io/
Keywords: python perfmetrics statsd
Platform: UNKNOWN
Classifier: Development Status :: 7 - Inactive
Classifier: Intended Audience :: Developers
Classifier: License :: OSI Approved :: Apache Software License
Classifier: Natural Language :: English
Classifier: Operating System :: OS Independent
Classifier: Programming Language :: Python :: 2
Classifier: Programming Language :: Python :: 2.7
Classifier: Programming Language :: Python :: 3
Classifier: Programming Language :: Python :: 3.5
Classifier: Programming Language :: Python :: 3.6
Classifier: Programming Language :: Python :: 3.7
Classifier: Programming Language :: Python :: Implementation :: CPython
Classifier: Programming Language :: Python :: Implementation :: PyPy
Requires-Dist: perfmetrics (>=3.0.0)
Requires-Dist: setuptools
Provides-Extra: docs
Requires-Dist: Sphinx ; extra == 'docs'
Requires-Dist: nti.testing ; extra == 'docs'
Requires-Dist: repoze.sphinx.autointerface ; extra == 'docs'
Requires-Dist: sphinx-rtd-theme ; extra == 'docs'
Provides-Extra: test
Requires-Dist: pyhamcrest ; extra == 'test'
Requires-Dist: nti.testing ; extra == 'test'
Requires-Dist: zope.testrunner ; extra == 'test'
